[ {
  "id" : "56c2e6ec-e5c2-41d4-b96b-fa7329a5f343",
  "layout" : "......0..1.2.0....230..1.2334415333...5536.775666",
  "queens" : "......Q....Q...........Q....Q....Q....Q....Q....Q",
  "pieceKind" : "BOTTOM_RIGHT",
  "pieceCategory" : "BOTH",
  "boardSize" : 7,
  "orthogonalMinDistance" : 5,
  "targetQueenCount" : 8,
  "queenCount" : 8,
  "leftBlackoutSignature" : [ 3, 1, 4, 2, 0, 3, 1 ],
  "topBlackoutSignature" : [ 0, 3, 1, 4, 1, 2, 0 ],
  "leftBlackoutFingerprint" : "06dd2524357abb7d99f9cd013e13b2af8d81da6c",
  "topBlackoutFingerprint" : "37bc08138ae24dd4a5d2d1b23c08597dc8e43f1f",
  "fingerprintKey" : "06dd2524357abb7d99f9cd013e13b2af8d81da6c:37bc08138ae24dd4a5d2d1b23c08597dc8e43f1f",
  "generationStrategy" : "baseline"
} ]