[ {
  "id" : "dffdc1fa-288c-4ab9-b39b-0ca41789547d",
  "layout" : "....0....1.02.....22...3332.4433556...5556.775566",
  "queens" : "....Q....Q.........Q....Q...Q..........Q...Q....Q",
  "pieceKind" : "BOTTOM_RIGHT",
  "pieceCategory" : "BOTH",
  "boardSize" : 7,
  "orthogonalMinDistance" : 5,
  "targetQueenCount" : 8,
  "queenCount" : 8,
  "leftBlackoutSignature" : [ 3, 1, 4, 2, 0, 3, 1 ],
  "topBlackoutSignature" : [ 4, 2, 0, 3, 0, 1, 4 ],
  "leftBlackoutFingerprint" : "06dd2524357abb7d99f9cd013e13b2af8d81da6c",
  "topBlackoutFingerprint" : "3b4da7de576cb3945696d41efe74f7d0d592c066",
  "fingerprintKey" : "06dd2524357abb7d99f9cd013e13b2af8d81da6c:3b4da7de576cb3945696d41efe74f7d0d592c066",
  "generationStrategy" : "baseline"
} ]