[ {
  "id" : "686c8f03-cbf1-4a6f-bb6a-b64d520c914f",
  "layout" : "...0....1.0..2.1.33.2..443.5....555.666657...6677",
  "queens" : "...Q....Q....Q....Q....Q.........Q....Q.........Q",
  "pieceKind" : "BOTTOM_RIGHT",
  "pieceCategory" : "BOTH",
  "boardSize" : 7,
  "orthogonalMinDistance" : 5,
  "targetQueenCount" : 8,
  "queenCount" : 8,
  "leftBlackoutSignature" : [ 1, 0, 0, 2, 4, 1, 3 ],
  "topBlackoutSignature" : [ 4, 1, 3, 0, 2, 4, 1 ],
  "leftBlackoutFingerprint" : "34d2f12238f6e0286aa51eb87d40b8ab3cd3bdba",
  "topBlackoutFingerprint" : "e83feb4d0f4546a5f693405ed0e411bcf7f7eedb",
  "fingerprintKey" : "34d2f12238f6e0286aa51eb87d40b8ab3cd3bdba:e83feb4d0f4546a5f693405ed0e411bcf7f7eedb",
  "generationStrategy" : "baseline"
} ]