[ {
  "id" : "69b90626-176d-45de-ae4d-d7edb370f0a2",
  "layout" : "....0......0.122.30.1...3341....444.555644...6666",
  "queens" : "....Q..........Q....Q...Q........Q...Q........Q..",
  "pieceKind" : "BOTTOM_RIGHT",
  "pieceCategory" : "BOTH",
  "boardSize" : 7,
  "orthogonalMinDistance" : 5,
  "targetQueenCount" : 7,
  "queenCount" : 7,
  "leftBlackoutSignature" : [ 1, 3, 0, 2, 4, 1, 3 ],
  "topBlackoutSignature" : [ 0, 1, 4, 2, 0, 3, 1 ],
  "leftBlackoutFingerprint" : "4377762aad49eddb0d6f3ceae9f38d11569d6acd",
  "topBlackoutFingerprint" : "a194b8b5f3a69694e49dd2de8102f5e223db33cc",
  "fingerprintKey" : "4377762aad49eddb0d6f3ceae9f38d11569d6acd:a194b8b5f3a69694e49dd2de8102f5e223db33cc",
  "generationStrategy" : "baseline"
} ]