[ {
  "id" : "daa9cfcf-37cc-45df-a566-8ea23f2c55fe",
  "layout" : "0001222...1123.441533....553.6665778869777...9977",
  "queens" : "Q....Q....Q....Q....Q....Q....Q....Q....Q....Q...",
  "pieceKind" : "TOP_RIGHT",
  "pieceCategory" : "LEFT_ONLY",
  "boardSize" : 7,
  "orthogonalMinDistance" : 5,
  "targetQueenCount" : 10,
  "queenCount" : 10,
  "leftBlackoutSignature" : [ 0, 3, 1, 4, 1, 0, 3 ],
  "topBlackoutSignature" : [ 0, 0, 0, 0, 0, 0, 0 ],
  "leftBlackoutFingerprint" : "6dacf282b1f7328d9745545808496469a39c1f48",
  "topBlackoutFingerprint" : "",
  "fingerprintKey" : "6dacf282b1f7328d9745545808496469a39c1f48:",
  "generationStrategy" : "baseline"
} ]