[ {
  "id" : "663b34bf-59a2-48ca-b0be-4ed955183fca",
  "layout" : ".0......0.1.2......2..333.224433526...55567775566",
  "queens" : ".Q........Q........Q...Q....Q..........Q...Q....Q",
  "pieceKind" : "BOTTOM_RIGHT",
  "pieceCategory" : "BOTH",
  "boardSize" : 7,
  "orthogonalMinDistance" : 5,
  "targetQueenCount" : 8,
  "queenCount" : 8,
  "leftBlackoutSignature" : [ 0, 1, 4, 1, 0, 3, 0 ],
  "topBlackoutSignature" : [ 3, 0, 2, 1, 4, 1, 3 ],
  "leftBlackoutFingerprint" : "a07c63995fb23772e4fcbdc3e04221f974e236d1",
  "topBlackoutFingerprint" : "00a43d50437b1184190b2e1c994c661074cb518a",
  "fingerprintKey" : "a07c63995fb23772e4fcbdc3e04221f974e236d1:00a43d50437b1184190b2e1c994c661074cb518a",
  "generationStrategy" : "baseline"
} ]